amrita_plugin_exec/__init__.py
amrita_plugin_exec/config.py
amrita_plugin_exec/container_exec.py
amrita_plugin_exec/main.py
amrita_plugin_exec-0.1.2.post1.dist-info/licenses/LICENSE
amrita_plugin_exec-0.1.2.post1.dist-info/METADATA
amrita_plugin_exec-0.1.2.post1.dist-info/WHEEL
amrita_plugin_exec-0.1.2.post1.dist-info/top_level.txt
amrita_plugin_exec-0.1.2.post1.dist-info/RECORD
