Metadata-Version: 2.4
Name: amrita-plugin-exec
Version: 0.1.2.post1
Summary: Command execution plugin for Amrita
Requires-Python: <3.14,>=3.10
License-File: LICENSE
Requires-Dist: amrita[full]>=0.4.2
Requires-Dist: docker>=6.0.0
Dynamic: license-file
